darbiadev_shipping/__init__.py
darbiadev_shipping/py.typed
darbiadev_shipping/shipping_services.py
darbiadev_shipping-0.5.1.dist-info/LICENSE
darbiadev_shipping-0.5.1.dist-info/METADATA
darbiadev_shipping-0.5.1.dist-info/WHEEL
darbiadev_shipping-0.5.1.dist-info/top_level.txt
darbiadev_shipping-0.5.1.dist-info/RECORD
