Metadata-Version: 2.1
Name: darbiadev-shipping
Version: 0.5.1
Summary: darbiadev-shipping
Author-email: Bradley Reynolds <bradley.reynolds@darbia.dev>
License: MIT
Project-URL: repository, https://github.com/darbiadev/darbiadev-shipping
Project-URL: documentation, https://docs.darbia.dev/darbiadev-shipping/
Requires-Python: <3.13,>=3.11
License-File: LICENSE
Provides-Extra: dev
Requires-Dist: pip-tools ; extra == 'dev'
Requires-Dist: pre-commit ; extra == 'dev'
Requires-Dist: ruff ; extra == 'dev'
Provides-Extra: docs
Requires-Dist: sphinx ; extra == 'docs'
Requires-Dist: furo ; extra == 'docs'
Requires-Dist: sphinx-autoapi ; extra == 'docs'
Requires-Dist: releases ; extra == 'docs'
Provides-Extra: fedex
Requires-Dist: darbiadev-fedex <1.0.0,>=0.3.0 ; extra == 'fedex'
Provides-Extra: tests
Requires-Dist: pytest ; extra == 'tests'
Requires-Dist: pytest-randomly ; extra == 'tests'
Provides-Extra: ups
Requires-Dist: darbiadev-ups <1.0.0,>=0.5.0 ; extra == 'ups'
Provides-Extra: usps
Requires-Dist: darbiadev-usps <1.0.0,>=0.5.0 ; extra == 'usps'
